jazelle-0.1.1.dist-info/WHEEL
jazelle-0.1.1.dist-info/METADATA
jazelle-0.1.1.dist-info/RECORD
jazelle-0.1.1.dist-info/licenses/LICENSE
jazelle/jazelle_cython.pxd
jazelle/jazelle_cython.so
jazelle/jazelle_cython.pyx
jazelle/__init__.py
jazelle/libcpp/chrono.pxd
jazelle/libcpp/__init__.py
