Metadata-Version: 2.2
Name: jazelle
Version: 0.1.1
Summary: A fast reader for SLD Jazelle files.
Author-Email: Alkaid Cheng <alkaid.ccheng@gmail.com>
License: MIT License
Classifier: Programming Language :: Python :: 3
Classifier: Programming Language :: C++
Classifier: License :: OSI Approved :: MIT License
Classifier: Operating System :: OS Independent
Requires-Python: >=3.8
